MANIFEST.in
README.md
setup.py
version.py
commodity/__init__.py
commodity/args.py
commodity/deco.py
commodity/excepts.py
commodity/fs.py
commodity/log.py
commodity/mail.py
commodity/net.py
commodity/os_.py
commodity/path.py
commodity/pattern.py
commodity/sequences.py
commodity/str_.py
commodity/term.py
commodity/testing.py
commodity/thread_.py
commodity/type_.py
commodity/version.py
commodity.egg-info/PKG-INFO
commodity.egg-info/SOURCES.txt
commodity.egg-info/dependency_links.txt
commodity.egg-info/top_level.txt
test/testing_tests.py